pyputio/__init__.py
pyputio/empty.py
pyputio/main.py
pyputio/plex.py
pyputio/scan.py
pyputio-0.1.21.dist-info/METADATA
pyputio-0.1.21.dist-info/WHEEL
pyputio-0.1.21.dist-info/entry_points.txt
pyputio-0.1.21.dist-info/top_level.txt
pyputio-0.1.21.dist-info/RECORD
