Metadata-Version: 2.1
Name: pyputio
Version: 0.1.21
Summary: Command Line Client for Put.io download zip archives
Home-page: https://github.com/jmarhee/pyputio-cli
Author: jmarhee
Author-email: jmarhee@interiorae.com
License: MIT
Requires-Python: >=3.8
Requires-Dist: progressbar
Requires-Dist: requests
Requires-Dist: plexapi
